textanalyzer/__init__.py
textanalyzer/processors/__init__.py
textanalyzer/processors/base.py
textanalyzer/processors/dedup.py
textanalyzer/processors/stats.py
textanalyzer/utils/__init__.py
textanalyzer-0.1.1.dist-info/LICENSE
textanalyzer-0.1.1.dist-info/METADATA
textanalyzer-0.1.1.dist-info/WHEEL
textanalyzer-0.1.1.dist-info/top_level.txt
textanalyzer-0.1.1.dist-info/RECORD
